error_libary/__init__.py
error_libary/types_errors.py
errorLibary-0.0.6.dist-info/METADATA
errorLibary-0.0.6.dist-info/WHEEL
errorLibary-0.0.6.dist-info/top_level.txt
errorLibary-0.0.6.dist-info/RECORD
