Metadata-Version: 2.1
Name: errorLibary
Version: 0.0.6
Summary: Personal Error Handling Library.
Home-page: https://github.com/DoK2412/error_lidrary
Author: dok2412
Author-email: i@dok2412.ru
Project-URL: GitHub, https://github.com/DoK2412/error_lidrary
Keywords: files speedfiles
Classifier: Programming Language :: Python :: 3.12
Classifier: License :: OSI Approved :: MIT License
Classifier: Operating System :: OS Independent
Requires-Python: >=3.12
Requires-Dist: requests>=2.25.1
